typed_ray/__init__.py
typed_ray/__init__.pyi
typed_ray/_version.py
typed_ray/_version.pyi
typed_ray/build_ray_types.py
typed_ray/build_ray_types.pyi
typed_ray/callbacks/__init__.py
typed_ray/callbacks/__init__.pyi
typed_ray/callbacks/actor_handle_type_callback.py
typed_ray/callbacks/actor_handle_type_callback.pyi
typed_ray/callbacks/remote_decorator_callback.py
typed_ray/callbacks/remote_decorator_callback.pyi
typed_ray/callbacks.pyi
typed_ray/constants.py
typed_ray/constants.pyi
typed_ray/main.py
typed_ray/main.pyi
typed_ray/mypy_types.py
typed_ray/mypy_types.pyi
typed_ray/ray_types.py
typed_ray/ray_types.pyi
typed_ray/typed_ray.py
typed_ray/typed_ray.pyi
typed_ray/utils.py
typed_ray/utils.pyi
typed_ray-0.2.6.dist-info/WHEEL
typed_ray-0.2.6.dist-info/METADATA
typed_ray-0.2.6.dist-info/RECORD
